my_package/__init__.py
my_package/module.py
jupter-0.1.0.dist-info/METADATA
jupter-0.1.0.dist-info/WHEEL
jupter-0.1.0.dist-info/top_level.txt
jupter-0.1.0.dist-info/RECORD
