Metadata-Version: 2.1
Name: jupter
Version: 0.1.0
Summary: A package with useful functions like nothing
Author: Hisham
Author-email: hishamraihann40@gmail.com
Requires-Python: >=2.1
